keqing/__init__.py
keqing-1.0.2.dist-info/entry_points.txt
keqing-1.0.2.dist-info/LICENSE
keqing-1.0.2.dist-info/METADATA
keqing-1.0.2.dist-info/WHEEL
keqing-1.0.2.dist-info/RECORD
