Metadata-Version: 2.1
Name: keqing
Version: 1.0.2
Summary: A non-database Python base OSM data parser, with SQL operation simulated.
Home-page: https://github.com/OSMChina/Keqing
License: MIT
Author: 快乐的老鼠宝宝
Author-email: keaitianxinmail@qq.com
Requires-Python: >=3.8,<4.0
Classifier: License :: OSI Approved :: MIT License
Classifier: Operating System :: OS Independent
Classifier: Programming Language :: Python :: 3
Classifier: Programming Language :: Python :: 3.8
Classifier: Programming Language :: Python :: 3.9
Classifier: Programming Language :: Python :: 3.10
Classifier: Programming Language :: Python :: 3.11
Classifier: Programming Language :: Python :: 3
Requires-Dist: requests (>=2.28.2,<3.0.0)
Project-URL: Repository, https://github.com/OSMChina/Keqing
